aiolotus/__init__.py
aiolotus/client.py
aiolotus/main.py
aiolotus/operations.py
aiolotus/version.py
aiolotus/worker.py
aiolotus/schemas/__init__.py
aiolotus/schemas/base.py
aiolotus/schemas/customers.py
aiolotus/schemas/events.py
aiolotus/schemas/metrics.py
aiolotus/schemas/plans.py
aiolotus/schemas/subscriptions.py
aiolotus/schemas/users.py
aiolotus/types/__init__.py
aiolotus/types/errors.py
aiolotus/types/filters.py
aiolotus/types/options.py
aiolotus/types/plans.py
aiolotus/utils/__init__.py
aiolotus/utils/config.py
aiolotus/utils/funcs.py
aiolotus/utils/helpers.py
aiolotus/utils/logs.py
aiolotus-0.0.1.dist-info/LICENSE
aiolotus-0.0.1.dist-info/METADATA
aiolotus-0.0.1.dist-info/WHEEL
aiolotus-0.0.1.dist-info/top_level.txt
aiolotus-0.0.1.dist-info/RECORD
